stormqa/__init__.py
stormqa/main.py
stormqa/core/__init__.py
stormqa/core/db_sim.py
stormqa/core/history_manager.py
stormqa/core/loader.py
stormqa/core/network_sim.py
stormqa/core/ws_engine.py
stormqa/reporters/__init__.py
stormqa/reporters/main_reporter.py
stormqa/ui/__init__.py
stormqa/ui/app.py
stormqa/ui/index.html
stormqa/ui/package-lock.json
stormqa/ui/package.json
stormqa/ui/postcss.config.js
stormqa/ui/tailwind.config.js
stormqa/ui/vite.config.js
stormqa/ui/dist/index.html
stormqa/ui/dist/assets/index-CVujZxDw.js
stormqa/ui/dist/assets/index-gLGWxX6i.css
stormqa-3.0.2.dist-info/licenses/LICENSE
stormqa-3.0.2.dist-info/METADATA
stormqa-3.0.2.dist-info/WHEEL
stormqa-3.0.2.dist-info/entry_points.txt
stormqa-3.0.2.dist-info/top_level.txt
stormqa-3.0.2.dist-info/RECORD
