Metadata-Version: 2.4
Name: stormqa
Version: 3.0.2
Summary: ⚡️ A zero-config, masterpiece tool for Load, Network, and DB testing (Modern Webview UI).
Author-email: Pouya Rezapour <pouyarezapourr@gmail.com>
License: MIT License
Project-URL: Homepage, https://github.com/pouyarer/StormQa
Project-URL: Repository, https://github.com/pouyarer/StormQa
Keywords: testing,qa,load testing,performance,gui,webview,react
Classifier: Programming Language :: Python :: 3
Classifier: License :: OSI Approved :: MIT License
Classifier: Operating System :: OS Independent
Classifier: Topic :: Software Development :: Testing
Classifier: Intended Audience :: Developers
Requires-Python: >=3.8
License-File: LICENSE
Requires-Dist: typer[all]
Requires-Dist: httpx
Requires-Dist: pywebview
Requires-Dist: packaging
Requires-Dist: pillow
Requires-Dist: fpdf2
Requires-Dist: websockets
Dynamic: license-file
